[
  {
    "path": "public/1701206151763_a.png.png",
    "mimetype": "image/png",
    "size": 405604,
    "meta": {
      "user": {
        "name": "Bayhan Bayramoglu",
        "email": "bayhan@contentrain.io",
        "avatar": null
      },
      "createdAt": "2023-11-27T12:48:31.970Z",
      "updatedAt": "2023-11-28T21:15:51.763Z"
    }
  },
  {
    "path": "public/1701200521722_Ekran Resmi 2023-11-21 12.27.19.png",
    "mimetype": "image/png",
    "size": 157462,
    "meta": {
      "user": {
        "name": "Bayhan Bayramoglu",
        "email": "bayhan@contentrain.io",
        "avatar": null
      },
      "createdAt": "2023-11-28T19:42:03.539Z"
    }
  }
]